<?xml version="1.0" encoding="UTF-8"?>
<objects serializationModel="Studio.02.00.00">
	<object class="EffectPreset" id="{e70e459e-e229-487f-92a6-3b498a91e749}">
		<property name="name">
			<value>Effect Chain</value>
		</property>
		<relationship name="folder">
			<destination>{0b88a44f-d726-4b89-9c97-57411123b949}</destination>
		</relationship>
		<relationship name="effect">
			<destination>{e66f05d4-1180-4ae5-9bf7-13096607b5fa}</destination>
		</relationship>
	</object>
	<object class="EffectChain" id="{e66f05d4-1180-4ae5-9bf7-13096607b5fa}" />
</objects>
