<?xml version="1.0" encoding="UTF-8"?>
<objects serializationModel="Studio.02.00.00">
	<object class="AudioFile" id="{e83c6abe-efc7-4e43-b28b-6954ffcc866e}">
		<property name="assetPath">
			<value>Character SFX/Footsteps/Footsteps, Barefoot, Dirt SND17366 1.9.wav</value>
		</property>
		<property name="frequencyInKHz">
			<value>44.0999985</value>
		</property>
		<property name="channelCount">
			<value>1</value>
		</property>
		<property name="length">
			<value>0.48591836734693877</value>
		</property>
		<relationship name="masterAssetFolder">
			<destination>{d47fbdba-3430-421a-9238-72af008289a8}</destination>
		</relationship>
	</object>
</objects>
